fetch-the-specs/__init__.py
fetch-the-specs/main.py
fetch_the_specs/__init__.py
fetch_the_specs/fetch_details.py
fetch_the_specs-1.0.1.dist-info/LICENSE
fetch_the_specs-1.0.1.dist-info/METADATA
fetch_the_specs-1.0.1.dist-info/WHEEL
fetch_the_specs-1.0.1.dist-info/entry_points.txt
fetch_the_specs-1.0.1.dist-info/top_level.txt
fetch_the_specs-1.0.1.dist-info/RECORD
