Metadata-Version: 2.1
Name: fetch-the-specs
Version: 1.0.1
Summary: A command-line tool to report system information in a colorful format.
Home-page: https://github.com/ibrahimhasnat/fetch-the-specs/
Author: Ibrahim Hasnat
License: UNKNOWN
Platform: UNKNOWN
Requires-Python: >=3.6
License-File: LICENSE
Requires-Dist: psutil
Requires-Dist: rich
